{
  "calendarDayTemperatureMax": [
    76,
    58,
    62,
    65,
    67,
    68,
    69,
    63
  ],
  "calendarDayTemperatureMin": [
    50,
    42,
    38,
    39,
    42,
    43,
    51,
    51
  ],
  "dayOfWeek": [
    "Friday",
    "Saturday",
    "Sunday",
    "Monday",
    "Tuesday",
    "Wednesday",
    "Thursday",
    "Friday"
  ],
  "expirationTimeUtc": [
    1665184401,
    1665184401,
    1665184401,
    1665184401,
    1665184401,
    1665184401,
    1665184401,
    1665184401
  ],
  "moonPhase": [
    "Waxing Gibbous",
    "Waxing Gibbous",
    "Full Moon",
    "Full Moon",
    "Waning Gibbous",
    "Waning Gibbous",
    "Waning Gibbous",
    "Waning Gibbous"
  ],
  "moonPhaseCode": [
    "WXG",
    "WXG",
    "F",
    "F",
    "WNG",
    "WNG",
    "WNG",
    "WNG"
  ],
  "moonPhaseDay": [
    12,
    13,
    14,
    15,
    16,
    17,
    18,
    19
  ],
  "moonriseTimeLocal": [
    "2022-10-07T17:51:43-0400",
    "2022-10-08T18:16:09-0400",
    "2022-10-09T18:40:05-0400",
    "2022-10-10T19:04:44-0400",
    "2022-10-11T19:31:13-0400",
    "2022-10-12T20:00:33-0400",
    "2022-10-13T20:34:38-0400",
    "2022-10-14T21:15:18-0400"
  ],
  "moonriseTimeUtc": [
    1665179503,
    1665267369,
    1665355205,
    1665443084,
    1665531073,
    1665619233,
    1665707678,
    1665796518
  ],
  "moonsetTimeLocal": [
    "2022-10-07T04:16:04-0400",
    "2022-10-08T05:28:25-0400",
    "2022-10-09T06:37:54-0400",
    "2022-10-10T07:46:56-0400",
    "2022-10-11T08:54:34-0400",
    "2022-10-12T10:01:48-0400",
    "2022-10-13T11:07:47-0400",
    "2022-10-14T12:10:34-0400"
  ],
  "moonsetTimeUtc": [
    1665130564,
    1665221305,
    1665311874,
    1665402416,
    1665492874,
    1665583308,
    1665673667,
    1665763834
  ],
  "narrative": [
    "Cloudy. Lows overnight in the mid 40s.",
    "Mainly sunny. Highs in the upper 50s and lows in the upper 30s.",
    "Abundant sunshine. Highs in the low 60s and lows in the upper 30s.",
    "A few clouds. Highs in the mid 60s and lows in the low 40s.",
    "Abundant sunshine. Highs in the upper 60s and lows in the low 40s.",
    "Partly cloudy. Highs in the upper 60s and lows in the low 50s.",
    "Showers possible in the afternoon. Highs in the upper 60s and lows in the mid 50s.",
    "A few morning showers. Highs in the low 60s and lows in the upper 40s."
  ],
  "qpf": [
    0,
    0,
    0,
    0,
    0,
    0,
    0.45,
    0.06
  ],
  "qpfSnow": [
    0,
    0,
    0,
    0,
    0,
    0,
    0,
    0
  ],
  "sunriseTimeLocal": [
    "2022-10-07T07:04:04-0400",
    "2022-10-08T07:05:06-0400",
    "2022-10-09T07:06:08-0400",
    "2022-10-10T07:07:10-0400",
    "2022-10-11T07:08:13-0400",
    "2022-10-12T07:09:16-0400",
    "2022-10-13T07:10:19-0400",
    "2022-10-14T07:11:22-0400"
  ],
  "sunriseTimeUtc": [
    1665140644,
    1665227106,
    1665313568,
    1665400030,
    1665486493,
    1665572956,
    1665659419,
    1665745882
  ],
  "sunsetTimeLocal": [
    "2022-10-07T18:33:58-0400",
    "2022-10-08T18:32:23-0400",
    "2022-10-09T18:30:48-0400",
    "2022-10-10T18:29:14-0400",
    "2022-10-11T18:27:42-0400",
    "2022-10-12T18:26:09-0400",
    "2022-10-13T18:24:38-0400",
    "2022-10-14T18:23:07-0400"
  ],
  "sunsetTimeUtc": [
    1665182038,
    1665268343,
    1665354648,
    1665440954,
    1665527262,
    1665613569,
    1665699878,
    1665786187
  ],
  "temperatureMax": [
    null,
    58,
    62,
    65,
    67,
    68,
    69,
    63
  ],
  "temperatureMin": [
    44,
    38,
    39,
    42,
    43,
    51,
    55,
    48
  ],
  "validTimeLocal": [
    "2022-10-07T07:00:00-0400",
    "2022-10-08T07:00:00-0400",
    "2022-10-09T07:00:00-0400",
    "2022-10-10T07:00:00-0400",
    "2022-10-11T07:00:00-0400",
    "2022-10-12T07:00:00-0400",
    "2022-10-13T07:00:00-0400",
    "2022-10-14T07:00:00-0400"
  ],
  "validTimeUtc": [
    1665140400,
    1665226800,
    1665313200,
    1665399600,
    1665486000,
    1665572400,
    1665658800,
    1665745200
  ],
  "daypart": [
    {
      "cloudCover": [
        null,
        78,
        15,
        8,
        4,
        6,
        24,
        10,
        4,
        20,
        52,
        47,
        71,
        78,
        48,
        37
      ],
      "dayOrNight": [
        null,
        "N",
        "D",
        "N",
        "D",
        "N",
        "D",
        "N",
        "D",
        "N",
        "D",
        "N",
        "D",
        "N",
        "D",
        "N"
      ],
      "daypartName": [
        null,
        "Tonight",
        "Tomorrow",
        "Tomorrow night",
        "Sunday",
        "Sunday night",
        "Monday",
        "Monday night",
        "Tuesday",
        "Tuesday night",
        "Wednesday",
        "Wednesday night",
        "Thursday",
        "Thursday night",
        "Friday",
        "Friday night"
      ],
      "iconCode": [
        null,
        26,
        32,
        31,
        32,
        31,
        34,
        33,
        32,
        33,
        30,
        29,
        39,
        11,
        39,
        29
      ],
      "iconCodeExtend": [
        null,
        2600,
        3200,
        3100,
        3200,
        3100,
        3400,
        3300,
        3200,
        3300,
        3000,
        2900,
        7103,
        1100,
        6103,
        2900
      ],
      "narrative": [
        null,
        "Cloudy. Slight chance of a shower throughout the evening. Low 44F. Winds NW at 5 to 10 mph.",
        "Sunny. Much cooler. High 58F. Winds NW at 5 to 10 mph.",
        "Clear skies. Low 38F. Winds light and variable.",
        "Sunny. High 62F. Winds W at 5 to 10 mph.",
        "Clear. Low 39F. Winds light and variable.",
        "Except for a few afternoon clouds, mainly sunny. High around 65F. Winds light and variable.",
        "A mostly clear sky. Low 42F. Winds light and variable.",
        "Sunny. High 67F. Winds light and variable.",
        "Clear skies with a few passing clouds. Low 43F. Winds light and variable.",
        "Intervals of clouds and sunshine. High 68F. Winds SSW at 5 to 10 mph.",
        "A few clouds from time to time. Low 51F. Winds light and variable.",
        "Increasing clouds with showers arriving sometime in the afternoon. High 69F. Winds S at 10 to 15 mph. Chance of rain 40%.",
        "Cloudy with showers. Low near 55F. Winds SSW at 5 to 10 mph. Chance of rain 60%.",
        "Showers in the morning, then partly cloudy in the afternoon. High 63F. Winds WNW at 5 to 10 mph. Chance of rain 60%.",
        "Partly cloudy. Low 48F. Winds light and variable."
      ],
      "precipChance": [
        null,
        15,
        3,
        4,
        4,
        4,
        5,
        6,
        6,
        7,
        7,
        15,
        41,
        58,
        58,
        24
      ],
      "precipType": [
        null,
        "rain",
        "rain",
        "precip",
        "rain",
        "precip",
        "rain",
        "rain",
        "rain",
        "rain",
        "rain",
        "rain",
        "rain",
        "rain",
        "rain",
        "rain"
      ],
      "qpf": [
        null,
        0,
        0,
        0,
        0,
        0,
        0,
        0,
        0,
        0,
        0,
        0,
        0.02,
        0.43,
        0.05,
        0
      ],
      "qpfSnow": [
        null,
        0,
        0,
        0,
        0,
        0,
        0,
        0,
        0,
        0,
        0,
        0,
        0,
        0,
        0,
        0
      ],
      "qualifierCode": [
        null,
        "Q5000",
        "Q760",
        null,
        null,
        null,
        null,
        null,
        null,
        null,
        null,
        null,
        null,
        null,
        null,
        null
      ],
      "qualifierPhrase": [
        null,
        "Slight chance of a shower throughout the evening.",
        "Much cooler.",
        null,
        null,
        null,
        null,
        null,
        null,
        null,
        null,
        null,
        null,
        null,
        null,
        null
      ],
      "relativeHumidity": [
        null,
        72,
        55,
        74,
        52,
        76,
        59,
        80,
        65,
        84,
        69,
        87,
        79,
        91,
        71,
        78
      ],
      "snowRange": [
        null,
        "",
        "",
        "",
        "",
        "",
        "",
        "",
        "",
        "",
        "",
        "",
        "",
        "",
        "",
        ""
      ],
      "temperature": [
        null,
        44,
        58,
        38,
        62,
        39,
        65,
        42,
        67,
        43,
        68,
        51,
        69,
        55,
        63,
        48
      ],
      "temperatureHeatIndex": [
        null,
        67,
        58,
        51,
        62,
        54,
        65,
        57,
        67,
        59,
        68,
        60,
        69,
        64,
        63,
        57
      ],
      "temperatureWindChill": [
        null,
        44,
        43,
        38,
        39,
        39,
        40,
        42,
        43,
        43,
        44,
        51,
        51,
        55,
        55,
        47
      ],
      "thunderCategory": [
        null,
        "No thunder",
        "No thunder",
        "No thunder",
        "No thunder",
        "No thunder",
        "No thunder",
        "No thunder",
        "No thunder",
        "No thunder",
        "No thunder",
        "No thunder",
        "No thunder",
        "No thunder",
        "No thunder",
        "No thunder"
      ],
      "thunderIndex": [
        null,
        0,
        0,
        0,
        0,
        0,
        0,
        0,
        0,
        0,
        0,
        0,
        0,
        0,
        0,
        0
      ],
      "uvDescription": [
        null,
        "Low",
        "Moderate",
        "Low",
        "Moderate",
        "Low",
        "Moderate",
        "Low",
        "Moderate",
        "Low",
        "Moderate",
        "Low",
        "Moderate",
        "Low",
        "Moderate",
        "Low"
      ],
      "uvIndex": [
        null,
        0,
        5,
        0,
        5,
        0,
        5,
        0,
        5,
        0,
        4,
        0,
        4,
        0,
        5,
        0
      ],
      "windDirection": [
        null,
        321,
        310,
        266,
        262,
        257,
        269,
        270,
        298,
        256,
        193,
        173,
        178,
        201,
        283,
        306
      ],
      "windDirectionCardinal": [
        null,
        "NW",
        "NW",
        "W",
        "W",
        "WSW",
        "W",
        "W",
        "WNW",
        "WSW",
        "SSW",
        "S",
        "S",
        "SSW",
        "WNW",
        "NW"
      ],
      "windPhrase": [
        null,
        "Winds NW at 5 to 10 mph.",
        "Winds NW at 5 to 10 mph.",
        "Winds light and variable.",
        "Winds W at 5 to 10 mph.",
        "Winds light and variable.",
        "Winds light and variable.",
        "Winds light and variable.",
        "Winds light and variable.",
        "Winds light and variable.",
        "Winds SSW at 5 to 10 mph.",
        "Winds light and variable.",
        "Winds S at 10 to 15 mph.",
        "Winds SSW at 5 to 10 mph.",
        "Winds WNW at 5 to 10 mph.",
        "Winds light and variable."
      ],
      "windSpeed": [
        null,
        6,
        9,
        3,
        9,
        3,
        6,
        3,
        5,
        2,
        7,
        5,
        11,
        8,
        10,
        6
      ],
      "wxPhraseLong": [
        null,
        "Cloudy",
        "Sunny",
        "Clear",
        "Sunny",
        "Clear",
        "Mostly Sunny",
        "Mostly Clear",
        "Sunny",
        "Mostly Clear",
        "Partly Cloudy",
        "Partly Cloudy",
        "PM Showers",
        "Showers",
        "AM Showers",
        "Partly Cloudy"
      ],
      "wxPhraseShort": [
        null,
        "Cloudy",
        "Sunny",
        "Clear",
        "Sunny",
        "Clear",
        "M Sunny",
        "M Clear",
        "Sunny",
        "M Clear",
        "P Cloudy",
        "P Cloudy",
        "PM Showers",
        "Showers",
        "AM Showers",
        "P Cloudy"
      ]
    }
  ]
}
