{
  "calendarDayTemperatureMax": [
    33,
    31,
    27,
    35,
    41,
    46,
    55,
    50
  ],
  "calendarDayTemperatureMin": [
    26,
    13,
    11,
    14,
    19,
    29,
    39,
    19
  ],
  "dayOfWeek": [
    "Friday",
    "Saturday",
    "Sunday",
    "Monday",
    "Tuesday",
    "Wednesday",
    "Thursday",
    "Friday"
  ],
  "expirationTimeUtc": [
    1643400607,
    1643400607,
    1643400607,
    1643400607,
    1643400607,
    1643400607,
    1643400607,
    1643400607
  ],
  "moonPhase": [
    "Waning Crescent",
    "Waning Crescent",
    "Waning Crescent",
    "New Moon",
    "New Moon",
    "Waxing Crescent",
    "Waxing Crescent",
    "Waxing Crescent"
  ],
  "moonPhaseCode": [
    "WNC",
    "WNC",
    "WNC",
    "N",
    "N",
    "WXC",
    "WXC",
    "WXC"
  ],
  "moonPhaseDay": [
    25,
    27,
    28,
    29,
    0,
    1,
    2,
    4
  ],
  "moonriseTimeLocal": [
    "2022-01-28T03:55:10-0500",
    "2022-01-29T05:07:55-0500",
    "2022-01-30T06:13:25-0500",
    "2022-01-31T07:07:46-0500",
    "2022-02-01T07:51:47-0500",
    "2022-02-02T08:27:37-0500",
    "2022-02-03T08:57:01-0500",
    "2022-02-04T09:22:35-0500"
  ],
  "moonriseTimeUtc": [
    1643360110,
    1643450875,
    1643541205,
    1643630866,
    1643719907,
    1643808457,
    1643896621,
    1643984555
  ],
  "moonsetTimeLocal": [
    "2022-01-28T13:15:59-0500",
    "2022-01-29T14:14:06-0500",
    "2022-01-30T15:21:58-0500",
    "2022-01-31T16:37:21-0500",
    "2022-02-01T17:53:32-0500",
    "2022-02-02T19:07:47-0500",
    "2022-02-03T20:18:49-0500",
    "2022-02-04T21:25:37-0500"
  ],
  "moonsetTimeUtc": [
    1643393759,
    1643483646,
    1643574118,
    1643665041,
    1643756012,
    1643846867,
    1643937529,
    1644027937
  ],
  "narrative": [
    "Chance of a few snow showers. Highs in the low 30s and lows in the low 20s.",
    "Snow early. Highs in the mid 20s and lows in the low teens.",
    "A few clouds. Highs in the upper 20s and lows in the mid teens.",
    "Partly cloudy. Highs in the mid 30s and lows in the upper teens.",
    "Mostly cloudy. Highs in the low 40s and lows in the upper 20s.",
    "Mostly cloudy. Highs in the mid 40s and lows in the upper 30s.",
    "Showers possible. Highs in the mid 50s and lows in the low 30s.",
    "Morning rain/snow. Highs in the mid 30s and lows in the mid teens."
  ],
  "qpf": [
    0.31,
    0.11,
    0,
    0,
    0,
    0.11,
    0.9,
    0.02
  ],
  "qpfSnow": [
    3.2,
    1.4,
    0,
    0,
    0,
    0,
    0,
    0.1
  ],
  "sunriseTimeLocal": [
    "2022-01-28T07:13:39-0500",
    "2022-01-29T07:12:48-0500",
    "2022-01-30T07:11:56-0500",
    "2022-01-31T07:11:03-0500",
    "2022-02-01T07:10:08-0500",
    "2022-02-02T07:09:11-0500",
    "2022-02-03T07:08:12-0500",
    "2022-02-04T07:07:13-0500"
  ],
  "sunriseTimeUtc": [
    1643372019,
    1643458368,
    1643544716,
    1643631063,
    1643717408,
    1643803751,
    1643890092,
    1643976433
  ],
  "sunsetTimeLocal": [
    "2022-01-28T17:15:41-0500",
    "2022-01-29T17:16:53-0500",
    "2022-01-30T17:18:05-0500",
    "2022-01-31T17:19:17-0500",
    "2022-02-01T17:20:29-0500",
    "2022-02-02T17:21:42-0500",
    "2022-02-03T17:22:54-0500",
    "2022-02-04T17:24:07-0500"
  ],
  "sunsetTimeUtc": [
    1643408141,
    1643494613,
    1643581085,
    1643667557,
    1643754029,
    1643840502,
    1643926974,
    1644013447
  ],
  "temperatureMax": [
    33,
    25,
    27,
    35,
    41,
    46,
    55,
    35
  ],
  "temperatureMin": [
    21,
    11,
    14,
    19,
    29,
    38,
    30,
    15
  ],
  "validTimeLocal": [
    "2022-01-28T07:00:00-0500",
    "2022-01-29T07:00:00-0500",
    "2022-01-30T07:00:00-0500",
    "2022-01-31T07:00:00-0500",
    "2022-02-01T07:00:00-0500",
    "2022-02-02T07:00:00-0500",
    "2022-02-03T07:00:00-0500",
    "2022-02-04T07:00:00-0500"
  ],
  "validTimeUtc": [
    1643371200,
    1643457600,
    1643544000,
    1643630400,
    1643716800,
    1643803200,
    1643889600,
    1643976000
  ],
  "daypart": [
    {
      "cloudCover": [
        95,
        100,
        89,
        16,
        24,
        59,
        62,
        34,
        67,
        78,
        81,
        97,
        97,
        86,
        45,
        47
      ],
      "dayOrNight": [
        "D",
        "N",
        "D",
        "N",
        "D",
        "N",
        "D",
        "N",
        "D",
        "N",
        "D",
        "N",
        "D",
        "N",
        "D",
        "N"
      ],
      "daypartName": [
        "Today",
        "Tonight",
        "Tomorrow",
        "Tomorrow night",
        "Sunday",
        "Sunday night",
        "Monday",
        "Monday night",
        "Tuesday",
        "Tuesday night",
        "Wednesday",
        "Wednesday night",
        "Thursday",
        "Thursday night",
        "Friday",
        "Friday night"
      ],
      "iconCode": [
        14,
        16,
        16,
        29,
        34,
        29,
        30,
        29,
        28,
        27,
        26,
        11,
        11,
        11,
        5,
        29
      ],
      "iconCodeExtend": [
        1400,
        1600,
        6903,
        2900,
        3400,
        2900,
        3000,
        2900,
        2800,
        2700,
        2600,
        1100,
        1100,
        1100,
        6403,
        2900
      ],
      "narrative": [
        "Snow showers. Temps nearly steady in the low to mid 30s. Winds light and variable. Chance of snow 40%.",
        "Periods of snow. Low 21F. Winds N at 10 to 20 mph. Chance of snow 100%. Snow accumulating 3 to 5 inches.",
        "Snow will taper off and end during the morning but skies will remain cloudy during the afternoon. High near 25F. Winds NW at 15 to 25 mph. Chance of snow 80%. Snow accumulating 1 to 3 inches.  Winds could occasionally gust over 40 mph.",
        "Some clouds early will give way to generally clear conditions overnight. Low 11F. Winds NW at 10 to 20 mph.",
        "Sunshine and some clouds. High 27F. Winds W at 5 to 10 mph.",
        "A few clouds. Low 14F. Winds light and variable.",
        "Mostly cloudy skies early, then partly cloudy in the afternoon. High around 35F. Winds light and variable.",
        "Partly cloudy. Low 19F. Winds light and variable.",
        "Mostly cloudy skies. High 41F. Winds light and variable.",
        "Mainly cloudy. Low 29F. Winds light and variable.",
        "Cloudy skies. High 46F. Winds light and variable.",
        "Rain showers in the evening becoming a steady light rain overnight. Low 38F. Winds light and variable. Chance of rain 80%.",
        "Cloudy with showers. High near 55F. Winds S at 10 to 15 mph. Chance of rain 60%.",
        "Cloudy with showers. Low around 30F. Winds WSW at 10 to 15 mph. Chance of rain 50%.",
        "Cloudy with rain and snow diminishing in the morning. Partial clearing in the afternoon. High around 35F. Winds NW at 10 to 15 mph. Chance of precip 30%.",
        "Partly cloudy. Low around 15F. Winds NNW at 5 to 10 mph."
      ],
      "precipChance": [
        42,
        95,
        84,
        2,
        2,
        7,
        5,
        8,
        8,
        9,
        16,
        75,
        55,
        54,
        30,
        8
      ],
      "precipType": [
        "snow",
        "snow",
        "snow",
        "snow",
        "precip",
        "snow",
        "precip",
        "snow",
        "rain",
        "precip",
        "rain",
        "rain",
        "rain",
        "rain",
        "precip",
        "snow"
      ],
      "qpf": [
        0,
        0.31,
        0.11,
        0,
        0,
        0,
        0,
        0,
        0,
        0,
        0,
        0.11,
        0.39,
        0.5,
        0.02,
        0
      ],
      "qpfSnow": [
        0.1,
        3.1,
        1.4,
        0,
        0,
        0,
        0,
        0,
        0,
        0,
        0,
        0,
        0,
        0,
        0.1,
        0
      ],
      "qualifierCode": [
        null,
        null,
        "Q1021",
        null,
        null,
        null,
        null,
        null,
        null,
        null,
        null,
        null,
        null,
        null,
        null,
        null
      ],
      "qualifierPhrase": [
        null,
        null,
        "Winds could occasionally gust over 40 mph.",
        null,
        null,
        null,
        null,
        null,
        null,
        null,
        null,
        null,
        null,
        null,
        null,
        null
      ],
      "relativeHumidity": [
        83,
        79,
        60,
        54,
        57,
        76,
        71,
        88,
        77,
        87,
        76,
        93,
        90,
        79,
        58,
        56
      ],
      "snowRange": [
        "",
        "3-5",
        "1-3",
        "",
        "",
        "",
        "",
        "",
        "",
        "",
        "",
        "",
        "",
        "",
        "",
        ""
      ],
      "temperature": [
        33,
        21,
        25,
        11,
        27,
        14,
        35,
        19,
        41,
        29,
        46,
        38,
        55,
        30,
        35,
        15
      ],
      "temperatureHeatIndex": [
        33,
        32,
        24,
        18,
        25,
        21,
        34,
        27,
        40,
        34,
        45,
        44,
        54,
        51,
        35,
        29
      ],
      "temperatureWindChill": [
        27,
        13,
        4,
        0,
        2,
        15,
        15,
        20,
        20,
        30,
        30,
        36,
        41,
        27,
        22,
        7
      ],
      "thunderCategory": [
        "No thunder",
        "No thunder",
        "No thunder",
        "No thunder",
        "No thunder",
        "No thunder",
        "No thunder",
        "No thunder",
        "No thunder",
        "No thunder",
        "No thunder",
        "No thunder",
        "No thunder",
        "No thunder",
        "No thunder",
        "No thunder"
      ],
      "thunderIndex": [
        0,
        0,
        0,
        0,
        0,
        0,
        0,
        0,
        0,
        0,
        0,
        0,
        0,
        0,
        0,
        0
      ],
      "uvDescription": [
        "Low",
        "Low",
        "Low",
        "Low",
        "Low",
        "Low",
        "Low",
        "Low",
        "Low",
        "Low",
        "Low",
        "Low",
        "Low",
        "Low",
        "Low",
        "Low"
      ],
      "uvIndex": [
        1,
        0,
        1,
        0,
        2,
        0,
        2,
        0,
        2,
        0,
        2,
        0,
        1,
        0,
        2,
        0
      ],
      "windDirection": [
        32,
        11,
        323,
        305,
        270,
        136,
        65,
        41,
        97,
        189,
        113,
        145,
        189,
        246,
        325,
        346
      ],
      "windDirectionCardinal": [
        "NNE",
        "N",
        "NW",
        "NW",
        "W",
        "SE",
        "ENE",
        "NE",
        "E",
        "S",
        "ESE",
        "SE",
        "S",
        "WSW",
        "NW",
        "NNW"
      ],
      "windPhrase": [
        "Winds light and variable.",
        "Winds N at 10 to 20 mph.",
        "Winds NW at 15 to 25 mph.",
        "Winds NW at 10 to 20 mph.",
        "Winds W at 5 to 10 mph.",
        "Winds light and variable.",
        "Winds light and variable.",
        "Winds light and variable.",
        "Winds light and variable.",
        "Winds light and variable.",
        "Winds light and variable.",
        "Winds light and variable.",
        "Winds S at 10 to 15 mph.",
        "Winds WSW at 10 to 15 mph.",
        "Winds NW at 10 to 15 mph.",
        "Winds NNW at 5 to 10 mph."
      ],
      "windSpeed": [
        6,
        15,
        17,
        16,
        8,
        2,
        3,
        3,
        3,
        2,
        4,
        4,
        11,
        11,
        13,
        8
      ],
      "wxPhraseLong": [
        "Snow Showers",
        "Snow",
        "AM Snow",
        "Partly Cloudy",
        "Mostly Sunny",
        "Partly Cloudy",
        "Partly Cloudy",
        "Partly Cloudy",
        "Mostly Cloudy",
        "Mostly Cloudy",
        "Cloudy",
        "Showers",
        "Showers",
        "Showers",
        "AM Rain/Snow",
        "Partly Cloudy"
      ],
      "wxPhraseShort": [
        "Snow Showers",
        "Snow",
        "AM Snow",
        "P Cloudy",
        "M Sunny",
        "P Cloudy",
        "P Cloudy",
        "P Cloudy",
        "M Cloudy",
        "M Cloudy",
        "Cloudy",
        "Showers",
        "Showers",
        "Showers",
        "AM Rain/Snow",
        "P Cloudy"
      ]
    }
  ]
}
