{
  "calendarDayTemperatureMax": [
    50,
    54,
    62,
    72,
    71,
    56,
    59,
    63
  ],
  "calendarDayTemperatureMin": [
    43,
    44,
    51,
    46,
    49,
    42,
    39,
    40
  ],
  "dayOfWeek": [
    "Monday",
    "Tuesday",
    "Wednesday",
    "Thursday",
    "Friday",
    "Saturday",
    "Sunday",
    "Monday"
  ],
  "expirationTimeUtc": [
    1664845716,
    1664845716,
    1664845716,
    1664845716,
    1664845716,
    1664845716,
    1664845716,
    1664845716
  ],
  "moonPhase": [
    "Waxing Gibbous",
    "Waxing Gibbous",
    "Waxing Gibbous",
    "Waxing Gibbous",
    "Waxing Gibbous",
    "Waxing Gibbous",
    "Full Moon",
    "Full Moon"
  ],
  "moonPhaseCode": [
    "WXG",
    "WXG",
    "WXG",
    "WXG",
    "WXG",
    "WXG",
    "F",
    "F"
  ],
  "moonPhaseDay": [
    8,
    9,
    10,
    11,
    12,
    13,
    14,
    15
  ],
  "moonriseTimeLocal": [
    "2022-10-03T15:26:54-0400",
    "2022-10-04T16:13:52-0400",
    "2022-10-05T16:52:23-0400",
    "2022-10-06T17:24:24-0400",
    "2022-10-07T17:51:38-0400",
    "2022-10-08T18:16:07-0400",
    "2022-10-09T18:40:04-0400",
    "2022-10-10T19:04:45-0400"
  ],
  "moonriseTimeUtc": [
    1664825214,
    1664914432,
    1665003143,
    1665091464,
    1665179498,
    1665267367,
    1665355204,
    1665443085
  ],
  "moonsetTimeLocal": [
    "",
    "2022-10-04T00:31:56-0400",
    "2022-10-05T01:46:49-0400",
    "2022-10-06T03:02:14-0400",
    "2022-10-07T04:16:05-0400",
    "2022-10-08T05:28:24-0400",
    "2022-10-09T06:37:51-0400",
    "2022-10-10T07:46:51-0400"
  ],
  "moonsetTimeUtc": [
    null,
    1664857916,
    1664948809,
    1665039734,
    1665130565,
    1665221304,
    1665311871,
    1665402411
  ],
  "narrative": [
    "Rain. Lows overnight in the mid 40s.",
    "Rain. Highs in the low 50s with temperatures nearly steady overnight.",
    "Morning showers. Highs in the low 60s and lows in the mid 40s.",
    "More sun than clouds. Highs in the low 70s and lows in the low 50s.",
    "Sunny. Highs in the low 70s and lows in the low 40s.",
    "A few clouds. Highs in the mid 50s and lows in the upper 30s.",
    "Abundant sunshine. Highs in the upper 50s and lows in the low 40s.",
    "Sunshine. Highs in the low 60s and lows in the low 40s."
  ],
  "qpf": [
    0.87,
    1.06,
    0.05,
    0,
    0,
    0,
    0,
    0
  ],
  "qpfSnow": [
    0,
    0,
    0,
    0,
    0,
    0,
    0,
    0
  ],
  "sunriseTimeLocal": [
    "2022-10-03T06:59:57-0400",
    "2022-10-04T07:00:57-0400",
    "2022-10-05T07:01:58-0400",
    "2022-10-06T07:02:59-0400",
    "2022-10-07T07:04:00-0400",
    "2022-10-08T07:05:02-0400",
    "2022-10-09T07:06:04-0400",
    "2022-10-10T07:07:06-0400"
  ],
  "sunriseTimeUtc": [
    1664794797,
    1664881257,
    1664967718,
    1665054179,
    1665140640,
    1665227102,
    1665313564,
    1665400026
  ],
  "sunsetTimeLocal": [
    "2022-10-03T18:40:23-0400",
    "2022-10-04T18:38:45-0400",
    "2022-10-05T18:37:09-0400",
    "2022-10-06T18:35:32-0400",
    "2022-10-07T18:33:57-0400",
    "2022-10-08T18:32:22-0400",
    "2022-10-09T18:30:48-0400",
    "2022-10-10T18:29:14-0400"
  ],
  "sunsetTimeUtc": [
    1664836823,
    1664923125,
    1665009429,
    1665095732,
    1665182037,
    1665268342,
    1665354648,
    1665440954
  ],
  "temperatureMax": [
    null,
    52,
    62,
    72,
    71,
    56,
    59,
    63
  ],
  "temperatureMin": [
    44,
    51,
    46,
    50,
    42,
    39,
    40,
    43
  ],
  "validTimeLocal": [
    "2022-10-03T07:00:00-0400",
    "2022-10-04T07:00:00-0400",
    "2022-10-05T07:00:00-0400",
    "2022-10-06T07:00:00-0400",
    "2022-10-07T07:00:00-0400",
    "2022-10-08T07:00:00-0400",
    "2022-10-09T07:00:00-0400",
    "2022-10-10T07:00:00-0400"
  ],
  "validTimeUtc": [
    1664794800,
    1664881200,
    1664967600,
    1665054000,
    1665140400,
    1665226800,
    1665313200,
    1665399600
  ],
  "daypart": [
    {
      "cloudCover": [
        null,
        99,
        100,
        98,
        91,
        33,
        24,
        18,
        14,
        24,
        19,
        7,
        8,
        6,
        10,
        15
      ],
      "dayOrNight": [
        null,
        "N",
        "D",
        "N",
        "D",
        "N",
        "D",
        "N",
        "D",
        "N",
        "D",
        "N",
        "D",
        "N",
        "D",
        "N"
      ],
      "daypartName": [
        null,
        "Tonight",
        "Tomorrow",
        "Tomorrow night",
        "Wednesday",
        "Wednesday night",
        "Thursday",
        "Thursday night",
        "Friday",
        "Friday night",
        "Saturday",
        "Saturday night",
        "Sunday",
        "Sunday night",
        "Monday",
        "Monday night"
      ],
      "iconCode": [
        null,
        12,
        12,
        12,
        39,
        29,
        34,
        33,
        32,
        33,
        34,
        31,
        32,
        31,
        32,
        33
      ],
      "iconCodeExtend": [
        null,
        1200,
        1200,
        1200,
        6103,
        2900,
        3400,
        3300,
        3200,
        3300,
        3400,
        3100,
        3200,
        3100,
        3200,
        3300
      ],
      "narrative": [
        null,
        "Rain. Low 44F. Winds N at 10 to 15 mph. Chance of rain 100%. Rainfall possibly over one inch.",
        "Rain likely. High 52F. Winds N at 10 to 15 mph. Chance of rain 100%. Rainfall may reach one inch.  Locally heavy rainfall possible.",
        "Rain early...then remaining cloudy with showers late. Low 51F. Winds NNE at 10 to 15 mph. Chance of rain 80%. Rainfall around a quarter of an inch.",
        "Rain showers early with overcast skies later in the day. High 62F. Winds N at 5 to 10 mph. Chance of rain 50%.",
        "A few clouds. Low 46F. Winds light and variable.",
        "Mostly sunny skies. High 72F. Winds light and variable.",
        "A mostly clear sky. Low near 50F. Winds light and variable.",
        "A mainly sunny sky. High 71F. Winds W at 5 to 10 mph.",
        "Mostly clear skies. Low 42F. Winds NW at 5 to 10 mph.",
        "Mostly sunny skies. High 56F. Winds WNW at 10 to 15 mph.",
        "Clear skies. Low 39F. Winds WNW at 5 to 10 mph.",
        "Sunny skies. High 59F. Winds WNW at 5 to 10 mph.",
        "Clear skies. Low around 40F. Winds light and variable.",
        "A mainly sunny sky. High 63F. Winds WNW at 5 to 10 mph.",
        "A mostly clear sky. Low 43F. Winds light and variable."
      ],
      "precipChance": [
        null,
        100,
        95,
        82,
        48,
        16,
        11,
        6,
        8,
        4,
        4,
        3,
        3,
        5,
        5,
        9
      ],
      "precipType": [
        null,
        "rain",
        "rain",
        "rain",
        "rain",
        "rain",
        "rain",
        "rain",
        "rain",
        "rain",
        "rain",
        "precip",
        "rain",
        "rain",
        "rain",
        "rain"
      ],
      "qpf": [
        null,
        0.87,
        0.75,
        0.31,
        0.05,
        0,
        0,
        0,
        0,
        0,
        0,
        0,
        0,
        0,
        0,
        0
      ],
      "qpfSnow": [
        null,
        0,
        0,
        0,
        0,
        0,
        0,
        0,
        0,
        0,
        0,
        0,
        0,
        0,
        0,
        0
      ],
      "qualifierCode": [
        null,
        null,
        "Q5050",
        null,
        null,
        null,
        null,
        null,
        null,
        null,
        null,
        null,
        null,
        null,
        null,
        null
      ],
      "qualifierPhrase": [
        null,
        null,
        "Locally heavy rainfall possible.",
        null,
        null,
        null,
        null,
        null,
        null,
        null,
        null,
        null,
        null,
        null,
        null,
        null
      ],
      "relativeHumidity": [
        null,
        92,
        95,
        93,
        86,
        89,
        66,
        85,
        68,
        70,
        57,
        71,
        58,
        76,
        60,
        77
      ],
      "snowRange": [
        null,
        "",
        "",
        "",
        "",
        "",
        "",
        "",
        "",
        "",
        "",
        "",
        "",
        "",
        "",
        ""
      ],
      "temperature": [
        null,
        44,
        52,
        51,
        62,
        46,
        72,
        50,
        71,
        42,
        56,
        39,
        59,
        40,
        63,
        43
      ],
      "temperatureHeatIndex": [
        null,
        48,
        52,
        53,
        62,
        59,
        72,
        64,
        71,
        61,
        56,
        51,
        59,
        53,
        63,
        56
      ],
      "temperatureWindChill": [
        null,
        40,
        40,
        48,
        51,
        46,
        47,
        50,
        51,
        41,
        40,
        37,
        37,
        40,
        40,
        43
      ],
      "thunderCategory": [
        null,
        "No thunder",
        "No thunder",
        "No thunder",
        "No thunder",
        "No thunder",
        "No thunder",
        "No thunder",
        "No thunder",
        "No thunder",
        "No thunder",
        "No thunder",
        "No thunder",
        "No thunder",
        "No thunder",
        "No thunder"
      ],
      "thunderIndex": [
        null,
        0,
        0,
        0,
        0,
        0,
        0,
        0,
        0,
        0,
        0,
        0,
        0,
        0,
        0,
        0
      ],
      "uvDescription": [
        null,
        "Low",
        "Low",
        "Low",
        "Low",
        "Low",
        "Moderate",
        "Low",
        "Moderate",
        "Low",
        "Moderate",
        "Low",
        "Moderate",
        "Low",
        "Moderate",
        "Low"
      ],
      "uvIndex": [
        null,
        0,
        2,
        0,
        2,
        0,
        5,
        0,
        5,
        0,
        5,
        0,
        5,
        0,
        5,
        0
      ],
      "windDirection": [
        null,
        7,
        8,
        13,
        9,
        326,
        274,
        224,
        260,
        309,
        303,
        291,
        284,
        282,
        282,
        264
      ],
      "windDirectionCardinal": [
        null,
        "N",
        "N",
        "NNE",
        "N",
        "NW",
        "W",
        "SW",
        "W",
        "NW",
        "WNW",
        "WNW",
        "WNW",
        "WNW",
        "WNW",
        "W"
      ],
      "windPhrase": [
        null,
        "Winds N at 10 to 15 mph.",
        "Winds N at 10 to 15 mph.",
        "Winds NNE at 10 to 15 mph.",
        "Winds N at 5 to 10 mph.",
        "Winds light and variable.",
        "Winds light and variable.",
        "Winds light and variable.",
        "Winds W at 5 to 10 mph.",
        "Winds NW at 5 to 10 mph.",
        "Winds WNW at 10 to 15 mph.",
        "Winds WNW at 5 to 10 mph.",
        "Winds WNW at 5 to 10 mph.",
        "Winds light and variable.",
        "Winds WNW at 5 to 10 mph.",
        "Winds light and variable."
      ],
      "windSpeed": [
        null,
        11,
        12,
        10,
        9,
        3,
        3,
        3,
        9,
        8,
        10,
        6,
        9,
        5,
        7,
        4
      ],
      "wxPhraseLong": [
        null,
        "Rain",
        "Rain",
        "Rain",
        "AM Showers",
        "Partly Cloudy",
        "Mostly Sunny",
        "Mostly Clear",
        "Sunny",
        "Mostly Clear",
        "Mostly Sunny",
        "Clear",
        "Sunny",
        "Clear",
        "Sunny",
        "Mostly Clear"
      ],
      "wxPhraseShort": [
        null,
        "Rain",
        "Rain",
        "Rain",
        "AM Showers",
        "P Cloudy",
        "M Sunny",
        "M Clear",
        "Sunny",
        "M Clear",
        "M Sunny",
        "Clear",
        "Sunny",
        "Clear",
        "Sunny",
        "M Clear"
      ]
    }
  ]
}
