{
  "calendarDayTemperatureMax": [
    41,
    42,
    41,
    51,
    68,
    57,
    52,
    54
  ],
  "calendarDayTemperatureMin": [
    31,
    31,
    26,
    30,
    45,
    34,
    32,
    33
  ],
  "dayOfWeek": [
    "Tuesday",
    "Wednesday",
    "Thursday",
    "Friday",
    "Saturday",
    "Sunday",
    "Monday",
    "Tuesday"
  ],
  "expirationTimeUtc": [
    1638908441,
    1638908441,
    1638908441,
    1638908441,
    1638908441,
    1638908441,
    1638908441,
    1638908441
  ],
  "moonPhase": [
    "Waxing Crescent",
    "Waxing Crescent",
    "Waxing Crescent",
    "First Quarter",
    "Waxing Gibbous",
    "Waxing Gibbous",
    "Waxing Gibbous",
    "Waxing Gibbous"
  ],
  "moonPhaseCode": [
    "WXC",
    "WXC",
    "WXC",
    "FQ",
    "WXG",
    "WXG",
    "WXG",
    "WXG"
  ],
  "moonPhaseDay": [
    4,
    5,
    6,
    7,
    8,
    9,
    10,
    11
  ],
  "moonriseTimeLocal": [
    "2021-12-07T10:47:47-0500",
    "2021-12-08T11:30:00-0500",
    "2021-12-09T12:04:20-0500",
    "2021-12-10T12:32:47-0500",
    "2021-12-11T12:57:14-0500",
    "2021-12-12T13:19:43-0500",
    "2021-12-13T13:42:04-0500",
    "2021-12-14T14:05:20-0500"
  ],
  "moonriseTimeUtc": [
    1638892067,
    1638981000,
    1639069460,
    1639157567,
    1639245434,
    1639333183,
    1639420924,
    1639508720
  ],
  "moonsetTimeLocal": [
    "2021-12-07T20:16:55-0500",
    "2021-12-08T21:29:57-0500",
    "2021-12-09T22:40:52-0500",
    "2021-12-10T23:47:14-0500",
    "",
    "2021-12-12T00:51:06-0500",
    "2021-12-13T01:52:24-0500",
    "2021-12-14T02:53:12-0500"
  ],
  "moonsetTimeUtc": [
    1638926215,
    1639016997,
    1639107652,
    1639198034,
    null,
    1639288266,
    1639378344,
    1639468392
  ],
  "narrative": [
    "Partly cloudy. Highs in the low 40s and lows in the low 30s.",
    "Cloudy. Highs in the low 40s and lows in the mid 20s.",
    "Considerable cloudiness. Highs in the low 40s and lows in the low 30s.",
    "Considerable cloudiness. Highs in the low 50s and lows in the low 40s.",
    "Cloudy, periods of rain. Highs in the upper 60s and lows in the low 40s.",
    "Partly cloudy. Highs in the mid 40s and lows in the low 30s.",
    "Abundant sunshine. Highs in the low 50s and lows in the low 30s.",
    "More sun than clouds. Highs in the mid 50s and lows in the mid 30s."
  ],
  "qpf": [
    0,
    0,
    0,
    0.07,
    0.73,
    0,
    0,
    0
  ],
  "qpfSnow": [
    0,
    0,
    0,
    0,
    0,
    0,
    0,
    0
  ],
  "sunriseTimeLocal": [
    "2021-12-07T07:10:18-0500",
    "2021-12-08T07:11:10-0500",
    "2021-12-09T07:12:00-0500",
    "2021-12-10T07:12:49-0500",
    "2021-12-11T07:13:37-0500",
    "2021-12-12T07:14:24-0500",
    "2021-12-13T07:15:09-0500",
    "2021-12-14T07:15:52-0500"
  ],
  "sunriseTimeUtc": [
    1638879018,
    1638965470,
    1639051920,
    1639138369,
    1639224817,
    1639311264,
    1639397709,
    1639484152
  ],
  "sunsetTimeLocal": [
    "2021-12-07T16:36:08-0500",
    "2021-12-08T16:36:08-0500",
    "2021-12-09T16:36:12-0500",
    "2021-12-10T16:36:17-0500",
    "2021-12-11T16:36:25-0500",
    "2021-12-12T16:36:35-0500",
    "2021-12-13T16:36:47-0500",
    "2021-12-14T16:37:01-0500"
  ],
  "sunsetTimeUtc": [
    1638912968,
    1638999368,
    1639085772,
    1639172177,
    1639258585,
    1639344995,
    1639431407,
    1639517821
  ],
  "temperatureMax": [
    40,
    42,
    41,
    51,
    68,
    45,
    52,
    54
  ],
  "temperatureMin": [
    31,
    26,
    30,
    43,
    40,
    32,
    33,
    34
  ],
  "validTimeLocal": [
    "2021-12-07T07:00:00-0500",
    "2021-12-08T07:00:00-0500",
    "2021-12-09T07:00:00-0500",
    "2021-12-10T07:00:00-0500",
    "2021-12-11T07:00:00-0500",
    "2021-12-12T07:00:00-0500",
    "2021-12-13T07:00:00-0500",
    "2021-12-14T07:00:00-0500"
  ],
  "validTimeUtc": [
    1638878400,
    1638964800,
    1639051200,
    1639137600,
    1639224000,
    1639310400,
    1639396800,
    1639483200
  ],
  "daypart": [
    {
      "cloudCover": [
        48,
        94,
        90,
        18,
        66,
        75,
        75,
        94,
        98,
        94,
        29,
        11,
        8,
        14,
        25,
        34
      ],
      "dayOrNight": [
        "D",
        "N",
        "D",
        "N",
        "D",
        "N",
        "D",
        "N",
        "D",
        "N",
        "D",
        "N",
        "D",
        "N",
        "D",
        "N"
      ],
      "daypartName": [
        "Today",
        "Tonight",
        "Tomorrow",
        "Tomorrow night",
        "Thursday",
        "Thursday night",
        "Friday",
        "Friday night",
        "Saturday",
        "Saturday night",
        "Sunday",
        "Sunday night",
        "Monday",
        "Monday night",
        "Tuesday",
        "Tuesday night"
      ],
      "iconCode": [
        30,
        26,
        26,
        29,
        28,
        27,
        28,
        11,
        12,
        12,
        30,
        31,
        32,
        33,
        34,
        33
      ],
      "iconCodeExtend": [
        3000,
        2600,
        2600,
        2900,
        2800,
        2700,
        2800,
        1100,
        1200,
        1200,
        3000,
        3100,
        3200,
        3300,
        3400,
        3300
      ],
      "narrative": [
        "Sun and clouds mixed. High near 40F. Winds W at 5 to 10 mph.",
        "Cloudy. Low 31F. Winds light and variable.",
        "Cloudy. A few flurries or snow showers possible. High 42F. Winds light and variable.",
        "Partly cloudy skies. Low 26F. Winds WNW at 5 to 10 mph.",
        "A mix of clouds and sun in the morning followed by cloudy skies during the afternoon. High 41F. Winds W at 5 to 10 mph.",
        "Mostly cloudy skies. Low around 30F. Winds light and variable.",
        "Considerable cloudiness. High 51F. Winds light and variable.",
        "Considerable cloudiness with occasional rain showers. Low 43F. Winds SSE at 5 to 10 mph. Chance of rain 50%.",
        "Showers early, becoming a steady rain later in the day. Near record high temperatures. High 68F. Winds SSW at 10 to 20 mph. Chance of rain 80%. Rainfall around a quarter of an inch.",
        "Rain likely. Low near 40F. Winds W at 10 to 15 mph. Chance of rain 90%. Rainfall around a half an inch.",
        "Some clouds in the morning will give way to mainly sunny skies for the afternoon. High near 45F. Winds WNW at 10 to 20 mph.",
        "Clear. Low 32F. Winds light and variable.",
        "Mainly sunny. High 52F. Winds WSW at 5 to 10 mph.",
        "A mostly clear sky. Low 33F. Winds light and variable.",
        "Mostly sunny skies. High 54F. Winds light and variable.",
        "Generally fair. Low 34F. Winds light and variable."
      ],
      "precipChance": [
        0,
        2,
        15,
        3,
        3,
        7,
        24,
        49,
        77,
        91,
        13,
        5,
        5,
        9,
        7,
        11
      ],
      "precipType": [
        "precip",
        "precip",
        "rain",
        "precip",
        "rain",
        "precip",
        "rain",
        "rain",
        "rain",
        "rain",
        "rain",
        "precip",
        "rain",
        "precip",
        "rain",
        "precip"
      ],
      "qpf": [
        0,
        0,
        0,
        0,
        0,
        0,
        0,
        0.07,
        0.24,
        0.49,
        0,
        0,
        0,
        0,
        0,
        0
      ],
      "qpfSnow": [
        0,
        0,
        0,
        0,
        0,
        0,
        0,
        0,
        0,
        0,
        0,
        0,
        0,
        0,
        0,
        0
      ],
      "qualifierCode": [
        null,
        null,
        "Q7815",
        null,
        null,
        null,
        null,
        null,
        "Q615",
        null,
        null,
        null,
        null,
        null,
        null,
        null
      ],
      "qualifierPhrase": [
        null,
        null,
        "A few flurries or snow showers possible.",
        null,
        null,
        null,
        null,
        null,
        "Near record high temperatures.",
        null,
        null,
        null,
        null,
        null,
        null,
        null
      ],
      "relativeHumidity": [
        51,
        67,
        56,
        69,
        52,
        69,
        70,
        96,
        89,
        78,
        49,
        62,
        48,
        64,
        52,
        75
      ],
      "snowRange": [
        "",
        "",
        "",
        "",
        "",
        "",
        "",
        "",
        "",
        "",
        "",
        "",
        "",
        "",
        "",
        ""
      ],
      "temperature": [
        40,
        31,
        42,
        26,
        41,
        30,
        51,
        43,
        68,
        40,
        45,
        32,
        52,
        33,
        54,
        34
      ],
      "temperatureHeatIndex": [
        39,
        35,
        41,
        36,
        40,
        35,
        49,
        52,
        67,
        64,
        45,
        40,
        51,
        43,
        52,
        42
      ],
      "temperatureWindChill": [
        35,
        32,
        32,
        24,
        23,
        28,
        35,
        44,
        52,
        36,
        35,
        30,
        30,
        35,
        34,
        36
      ],
      "thunderCategory": [
        "No thunder",
        "No thunder",
        "No thunder",
        "No thunder",
        "No thunder",
        "No thunder",
        "No thunder",
        "No thunder",
        "No thunder",
        "No thunder",
        "No thunder",
        "No thunder",
        "No thunder",
        "No thunder",
        "No thunder",
        "No thunder"
      ],
      "thunderIndex": [
        0,
        0,
        0,
        0,
        0,
        0,
        0,
        0,
        0,
        0,
        0,
        0,
        0,
        0,
        0,
        0
      ],
      "uvDescription": [
        "Low",
        "Low",
        "Low",
        "Low",
        "Low",
        "Low",
        "Low",
        "Low",
        "Low",
        "Low",
        "Low",
        "Low",
        "Low",
        "Low",
        "Low",
        "Low"
      ],
      "uvIndex": [
        0,
        0,
        1,
        0,
        1,
        0,
        1,
        0,
        1,
        0,
        2,
        0,
        2,
        0,
        2,
        0
      ],
      "windDirection": [
        277,
        338,
        169,
        296,
        275,
        152,
        171,
        155,
        200,
        270,
        297,
        262,
        245,
        283,
        237,
        34
      ],
      "windDirectionCardinal": [
        "W",
        "NNW",
        "S",
        "WNW",
        "W",
        "SSE",
        "S",
        "SSE",
        "SSW",
        "W",
        "WNW",
        "W",
        "WSW",
        "WNW",
        "WSW",
        "NE"
      ],
      "windPhrase": [
        "Winds W at 5 to 10 mph.",
        "Winds light and variable.",
        "Winds light and variable.",
        "Winds WNW at 5 to 10 mph.",
        "Winds W at 5 to 10 mph.",
        "Winds light and variable.",
        "Winds light and variable.",
        "Winds SSE at 5 to 10 mph.",
        "Winds SSW at 10 to 20 mph.",
        "Winds W at 10 to 15 mph.",
        "Winds WNW at 10 to 20 mph.",
        "Winds light and variable.",
        "Winds WSW at 5 to 10 mph.",
        "Winds light and variable.",
        "Winds light and variable.",
        "Winds light and variable."
      ],
      "windSpeed": [
        6,
        1,
        3,
        7,
        6,
        4,
        4,
        6,
        14,
        11,
        13,
        6,
        8,
        4,
        5,
        2
      ],
      "wxPhraseLong": [
        "Partly Cloudy",
        "Cloudy",
        "Cloudy",
        "Partly Cloudy",
        "Mostly Cloudy",
        "Mostly Cloudy",
        "Mostly Cloudy",
        "Showers",
        "Rain",
        "Rain",
        "Partly Cloudy",
        "Clear",
        "Sunny",
        "Mostly Clear",
        "Mostly Sunny",
        "Mostly Clear"
      ],
      "wxPhraseShort": [
        "P Cloudy",
        "Cloudy",
        "Cloudy",
        "P Cloudy",
        "M Cloudy",
        "M Cloudy",
        "M Cloudy",
        "Showers",
        "Rain",
        "Rain",
        "P Cloudy",
        "Clear",
        "Sunny",
        "M Clear",
        "M Sunny",
        "M Clear"
      ]
    }
  ]
}
