{
  "calendarDayTemperatureMax": [
    51,
    53,
    55,
    55,
    63,
    64,
    64,
    61
  ],
  "calendarDayTemperatureMin": [
    30,
    31,
    29,
    32,
    38,
    41,
    41,
    41
  ],
  "dayOfWeek": [
    "Thursday",
    "Friday",
    "Saturday",
    "Sunday",
    "Monday",
    "Tuesday",
    "Wednesday",
    "Thursday"
  ],
  "expirationTimeUtc": [
    1636016261,
    1636016261,
    1636016261,
    1636016261,
    1636016261,
    1636016261,
    1636016261,
    1636016261
  ],
  "moonPhase": [
    "New Moon",
    "Waxing Crescent",
    "Waxing Crescent",
    "Waxing Crescent",
    "Waxing Crescent",
    "Waxing Crescent",
    "Waxing Crescent",
    "First Quarter"
  ],
  "moonPhaseCode": [
    "N",
    "WXC",
    "WXC",
    "WXC",
    "WXC",
    "WXC",
    "WXC",
    "FQ"
  ],
  "moonPhaseDay": [
    0,
    1,
    2,
    3,
    4,
    5,
    6,
    7
  ],
  "moonriseTimeLocal": [
    "2021-11-04T07:04:52-0400",
    "2021-11-05T08:23:18-0400",
    "2021-11-06T09:43:35-0400",
    "2021-11-07T10:00:24-0500",
    "2021-11-08T11:09:32-0500",
    "2021-11-09T12:07:54-0500",
    "2021-11-10T12:54:38-0500",
    "2021-11-11T13:31:38-0500"
  ],
  "moonriseTimeUtc": [
    1636023892,
    1636114998,
    1636206215,
    1636297224,
    1636387772,
    1636477674,
    1636566878,
    1636655498
  ],
  "moonsetTimeLocal": [
    "2021-11-04T17:58:56-0400",
    "2021-11-05T18:34:52-0400",
    "2021-11-06T19:19:03-0400",
    "2021-11-07T19:11:54-0500",
    "2021-11-08T20:14:42-0500",
    "2021-11-09T21:23:11-0500",
    "2021-11-10T22:34:42-0500",
    "2021-11-11T23:44:09-0500"
  ],
  "moonsetTimeUtc": [
    1636063136,
    1636151692,
    1636240743,
    1636330314,
    1636420482,
    1636510991,
    1636601682,
    1636692249
  ],
  "narrative": [
    "Mix of sun and clouds. Highs in the low 50s and lows in the low 30s.",
    "Mainly sunny. Highs in the low 50s and lows in the upper 20s.",
    "Plenty of sun. Highs in the mid 50s and lows in the low 30s.",
    "Partly cloudy. Highs in the mid 50s and lows in the upper 30s.",
    "Mainly sunny. Highs in the low 60s and lows in the low 40s.",
    "A few clouds. Highs in the mid 60s and lows in the low 40s.",
    "Partly cloudy. Highs in the mid 60s and lows in the low 40s.",
    "Partly cloudy. Highs in the low 60s and lows in the upper 40s."
  ],
  "qpf": [
    0,
    0,
    0,
    0,
    0,
    0,
    0,
    0.03
  ],
  "qpfSnow": [
    0,
    0,
    0,
    0,
    0,
    0,
    0,
    0
  ],
  "sunriseTimeLocal": [
    "2021-11-04T07:34:49-0400",
    "2021-11-05T07:35:58-0400",
    "2021-11-06T07:37:07-0400",
    "2021-11-07T06:38:16-0500",
    "2021-11-08T06:39:25-0500",
    "2021-11-09T06:40:35-0500",
    "2021-11-10T06:41:44-0500",
    "2021-11-11T06:42:53-0500"
  ],
  "sunriseTimeUtc": [
    1636025689,
    1636112158,
    1636198627,
    1636285096,
    1636371565,
    1636458035,
    1636544504,
    1636630973
  ],
  "sunsetTimeLocal": [
    "2021-11-04T17:55:17-0400",
    "2021-11-05T17:54:13-0400",
    "2021-11-06T17:53:10-0400",
    "2021-11-07T16:52:09-0500",
    "2021-11-08T16:51:09-0500",
    "2021-11-09T16:50:11-0500",
    "2021-11-10T16:49:15-0500",
    "2021-11-11T16:48:20-0500"
  ],
  "sunsetTimeUtc": [
    1636062917,
    1636149253,
    1636235590,
    1636321929,
    1636408269,
    1636494611,
    1636580955,
    1636667300
  ],
  "temperatureMax": [
    51,
    53,
    55,
    55,
    63,
    64,
    64,
    61
  ],
  "temperatureMin": [
    31,
    29,
    32,
    38,
    41,
    41,
    41,
    47
  ],
  "validTimeLocal": [
    "2021-11-04T07:00:00-0400",
    "2021-11-05T07:00:00-0400",
    "2021-11-06T07:00:00-0400",
    "2021-11-07T07:00:00-0500",
    "2021-11-08T07:00:00-0500",
    "2021-11-09T07:00:00-0500",
    "2021-11-10T07:00:00-0500",
    "2021-11-11T07:00:00-0500"
  ],
  "validTimeUtc": [
    1636023600,
    1636110000,
    1636196400,
    1636286400,
    1636372800,
    1636459200,
    1636545600,
    1636632000
  ],
  "daypart": [
    {
      "cloudCover": [
        41,
        21,
        2,
        4,
        20,
        46,
        56,
        29,
        8,
        9,
        14,
        36,
        34,
        39,
        53,
        69
      ],
      "dayOrNight": [
        "D",
        "N",
        "D",
        "N",
        "D",
        "N",
        "D",
        "N",
        "D",
        "N",
        "D",
        "N",
        "D",
        "N",
        "D",
        "N"
      ],
      "daypartName": [
        "Today",
        "Tonight",
        "Tomorrow",
        "Tomorrow night",
        "Saturday",
        "Saturday night",
        "Sunday",
        "Sunday night",
        "Monday",
        "Monday night",
        "Tuesday",
        "Tuesday night",
        "Wednesday",
        "Wednesday night",
        "Thursday",
        "Thursday night"
      ],
      "iconCode": [
        30,
        29,
        32,
        31,
        34,
        29,
        30,
        29,
        32,
        31,
        34,
        29,
        30,
        29,
        30,
        45
      ],
      "iconCodeExtend": [
        3000,
        2900,
        3200,
        3100,
        3400,
        2900,
        3000,
        2900,
        3200,
        3100,
        3400,
        2900,
        3000,
        2900,
        3000,
        7100
      ],
      "narrative": [
        "Partly to mostly cloudy. Widespread frost likely. High 51F. Winds light and variable.",
        "Partly cloudy skies. Widespread frost likely. Low 31F. Winds light and variable.",
        "Sunny. High 53F. Winds N at 5 to 10 mph.",
        "Clear skies. Low 29F. Winds light and variable.",
        "Generally sunny. High around 55F. Winds light and variable.",
        "Partly cloudy. Low 32F. Winds light and variable.",
        "Sunshine and clouds mixed. High around 55F. Winds light and variable.",
        "Partly cloudy skies. Low 38F. Winds light and variable.",
        "Sunny skies. High 63F. Winds WNW at 5 to 10 mph.",
        "A mostly clear sky. Low 41F. Winds light and variable.",
        "Generally sunny despite a few afternoon clouds. High 64F. Winds light and variable.",
        "Partly cloudy skies. Low 41F. Winds light and variable.",
        "Partly cloudy. High 64F. Winds WSW at 5 to 10 mph.",
        "A few clouds from time to time. Low 41F. Winds NNE at 5 to 10 mph.",
        "Sunshine and clouds mixed. High 61F. Winds SSE at 5 to 10 mph.",
        "Mostly cloudy during the evening. A few showers developing late. Low 47F. Winds light and variable. Chance of rain 30%."
      ],
      "precipChance": [
        3,
        4,
        4,
        6,
        6,
        5,
        5,
        5,
        5,
        7,
        7,
        6,
        6,
        5,
        11,
        30
      ],
      "precipType": [
        "rain",
        "precip",
        "rain",
        "precip",
        "rain",
        "precip",
        "rain",
        "precip",
        "rain",
        "rain",
        "rain",
        "rain",
        "rain",
        "rain",
        "rain",
        "rain"
      ],
      "qpf": [
        0,
        0,
        0,
        0,
        0,
        0,
        0,
        0,
        0,
        0,
        0,
        0,
        0,
        0,
        0,
        0.03
      ],
      "qpfSnow": [
        0,
        0,
        0,
        0,
        0,
        0,
        0,
        0,
        0,
        0,
        0,
        0,
        0,
        0,
        0,
        0
      ],
      "qualifierCode": [
        "Q3010",
        "Q3010",
        null,
        null,
        null,
        null,
        null,
        null,
        null,
        null,
        null,
        null,
        null,
        null,
        null,
        null
      ],
      "qualifierPhrase": [
        "Widespread frost likely.",
        "Widespread frost likely.",
        null,
        null,
        null,
        null,
        null,
        null,
        null,
        null,
        null,
        null,
        null,
        null,
        null,
        null
      ],
      "relativeHumidity": [
        64,
        82,
        54,
        82,
        58,
        84,
        60,
        82,
        65,
        93,
        67,
        88,
        66,
        80,
        70,
        90
      ],
      "snowRange": [
        "",
        "",
        "",
        "",
        "",
        "",
        "",
        "",
        "",
        "",
        "",
        "",
        "",
        "",
        "",
        ""
      ],
      "temperature": [
        51,
        31,
        53,
        29,
        55,
        32,
        55,
        38,
        63,
        41,
        64,
        41,
        64,
        41,
        61,
        47
      ],
      "temperatureHeatIndex": [
        50,
        44,
        52,
        43,
        53,
        45,
        54,
        44,
        61,
        49,
        62,
        50,
        62,
        53,
        59,
        53
      ],
      "temperatureWindChill": [
        31,
        32,
        29,
        31,
        30,
        33,
        33,
        36,
        36,
        40,
        41,
        41,
        42,
        40,
        42,
        46
      ],
      "thunderCategory": [
        "No thunder",
        "No thunder",
        "No thunder",
        "No thunder",
        "No thunder",
        "No thunder",
        "No thunder",
        "No thunder",
        "No thunder",
        "No thunder",
        "No thunder",
        "No thunder",
        "No thunder",
        "No thunder",
        "No thunder",
        "No thunder"
      ],
      "thunderIndex": [
        0,
        0,
        0,
        0,
        0,
        0,
        0,
        0,
        0,
        0,
        0,
        0,
        0,
        0,
        0,
        0
      ],
      "uvDescription": [
        "Moderate",
        "Low",
        "Moderate",
        "Low",
        "Moderate",
        "Low",
        "Moderate",
        "Low",
        "Moderate",
        "Low",
        "Moderate",
        "Low",
        "Moderate",
        "Low",
        "Moderate",
        "Low"
      ],
      "uvIndex": [
        3,
        0,
        3,
        0,
        3,
        0,
        3,
        0,
        3,
        0,
        3,
        0,
        3,
        0,
        3,
        0
      ],
      "windDirection": [
        8,
        342,
        355,
        346,
        61,
        33,
        352,
        331,
        302,
        286,
        290,
        269,
        246,
        15,
        160,
        153
      ],
      "windDirectionCardinal": [
        "N",
        "NNW",
        "N",
        "NNW",
        "ENE",
        "NNE",
        "N",
        "NNW",
        "WNW",
        "WNW",
        "WNW",
        "W",
        "WSW",
        "NNE",
        "SSE",
        "SSE"
      ],
      "windPhrase": [
        "Winds light and variable.",
        "Winds light and variable.",
        "Winds N at 5 to 10 mph.",
        "Winds light and variable.",
        "Winds light and variable.",
        "Winds light and variable.",
        "Winds light and variable.",
        "Winds light and variable.",
        "Winds WNW at 5 to 10 mph.",
        "Winds light and variable.",
        "Winds light and variable.",
        "Winds light and variable.",
        "Winds WSW at 5 to 10 mph.",
        "Winds NNE at 5 to 10 mph.",
        "Winds SSE at 5 to 10 mph.",
        "Winds light and variable."
      ],
      "windSpeed": [
        4,
        2,
        7,
        2,
        4,
        2,
        5,
        4,
        7,
        4,
        6,
        3,
        8,
        6,
        7,
        5
      ],
      "wxPhraseLong": [
        "Partly Cloudy",
        "Partly Cloudy",
        "Sunny",
        "Clear",
        "Mostly Sunny",
        "Partly Cloudy",
        "Partly Cloudy",
        "Partly Cloudy",
        "Sunny",
        "Clear",
        "Mostly Sunny",
        "Partly Cloudy",
        "Partly Cloudy",
        "Partly Cloudy",
        "Partly Cloudy",
        "Showers Late"
      ],
      "wxPhraseShort": [
        "P Cloudy",
        "P Cloudy",
        "Sunny",
        "Clear",
        "M Sunny",
        "P Cloudy",
        "P Cloudy",
        "P Cloudy",
        "Sunny",
        "Clear",
        "M Sunny",
        "P Cloudy",
        "P Cloudy",
        "P Cloudy",
        "P Cloudy",
        "Shwrs Late"
      ]
    }
  ]
}
