{
  "calendarDayTemperatureMax": [
    97,
    91,
    85,
    86,
    91,
    89,
    88,
    87
  ],
  "calendarDayTemperatureMin": [
    71,
    74,
    69,
    68,
    73,
    71,
    67,
    68
  ],
  "dayOfWeek": [
    "Sunday",
    "Monday",
    "Tuesday",
    "Wednesday",
    "Thursday",
    "Friday",
    "Saturday",
    "Sunday"
  ],
  "expirationTimeUtc": [
    1658678743,
    1658678743,
    1658678743,
    1658678743,
    1658678743,
    1658678743,
    1658678743,
    1658678743
  ],
  "moonPhase": [
    "Waning Crescent",
    "Waning Crescent",
    "Waning Crescent",
    "Waning Crescent",
    "New Moon",
    "Waxing Crescent",
    "Waxing Crescent",
    "Waxing Crescent"
  ],
  "moonPhaseCode": [
    "WNC",
    "WNC",
    "WNC",
    "WNC",
    "N",
    "WXC",
    "WXC",
    "WXC"
  ],
  "moonPhaseDay": [
    26,
    27,
    27,
    28,
    0,
    1,
    2,
    2
  ],
  "moonriseTimeLocal": [
    "2022-07-24T02:07:59-0400",
    "2022-07-25T02:48:08-0400",
    "2022-07-26T03:35:27-0400",
    "2022-07-27T04:28:26-0400",
    "2022-07-28T05:27:27-0400",
    "2022-07-29T06:28:33-0400",
    "2022-07-30T07:31:48-0400",
    "2022-07-31T08:34:12-0400"
  ],
  "moonriseTimeUtc": [
    1658642879,
    1658731688,
    1658820927,
    1658910506,
    1659000447,
    1659090513,
    1659180708,
    1659270852
  ],
  "moonsetTimeLocal": [
    "2022-07-24T17:41:26-0400",
    "2022-07-25T18:37:03-0400",
    "2022-07-26T19:27:51-0400",
    "2022-07-27T20:11:07-0400",
    "2022-07-28T20:48:15-0400",
    "2022-07-29T21:20:04-0400",
    "2022-07-30T21:47:17-0400",
    "2022-07-31T22:11:15-0400"
  ],
  "moonsetTimeUtc": [
    1658698886,
    1658788623,
    1658878071,
    1658967067,
    1659055695,
    1659144004,
    1659232037,
    1659319875
  ],
  "narrative": [
    "Times of sun and clouds. Highs in the upper 90s and lows in the low 80s.",
    "Afternoon showers and thunderstorms. Potential for severe thunderstorms. Highs in the low 90s and lows in the low 70s.",
    "Morning clouds followed by afternoon sun. Highs in the mid 80s and lows in the upper 60s.",
    "Mix of sun and clouds. Highs in the mid 80s and lows in the low 70s.",
    "Thunderstorms early. Highs in the low 90s and lows in the low 70s.",
    "Showers ending by midday. Highs in the upper 80s and lows in the upper 60s.",
    "Partly cloudy. Highs in the upper 80s and lows in the upper 60s.",
    "Considerable cloudiness. Highs in the upper 80s and lows in the upper 60s."
  ],
  "qpf": [
    0,
    0.44,
    0,
    0.06,
    0.12,
    0.09,
    0,
    0.02
  ],
  "qpfSnow": [
    0,
    0,
    0,
    0,
    0,
    0,
    0,
    0
  ],
  "sunriseTimeLocal": [
    "2022-07-24T05:52:43-0400",
    "2022-07-25T05:53:35-0400",
    "2022-07-26T05:54:27-0400",
    "2022-07-27T05:55:20-0400",
    "2022-07-28T05:56:13-0400",
    "2022-07-29T05:57:07-0400",
    "2022-07-30T05:58:01-0400",
    "2022-07-31T05:58:55-0400"
  ],
  "sunriseTimeUtc": [
    1658656363,
    1658742815,
    1658829267,
    1658915720,
    1659002173,
    1659088627,
    1659175081,
    1659261535
  ],
  "sunsetTimeLocal": [
    "2022-07-24T20:22:54-0400",
    "2022-07-25T20:22:02-0400",
    "2022-07-26T20:21:08-0400",
    "2022-07-27T20:20:13-0400",
    "2022-07-28T20:19:16-0400",
    "2022-07-29T20:18:18-0400",
    "2022-07-30T20:17:18-0400",
    "2022-07-31T20:16:17-0400"
  ],
  "sunsetTimeUtc": [
    1658708574,
    1658794922,
    1658881268,
    1658967613,
    1659053956,
    1659140298,
    1659226638,
    1659312977
  ],
  "temperatureMax": [
    97,
    91,
    85,
    86,
    91,
    89,
    88,
    87
  ],
  "temperatureMin": [
    80,
    70,
    68,
    73,
    71,
    67,
    68,
    69
  ],
  "validTimeLocal": [
    "2022-07-24T07:00:00-0400",
    "2022-07-25T07:00:00-0400",
    "2022-07-26T07:00:00-0400",
    "2022-07-27T07:00:00-0400",
    "2022-07-28T07:00:00-0400",
    "2022-07-29T07:00:00-0400",
    "2022-07-30T07:00:00-0400",
    "2022-07-31T07:00:00-0400"
  ],
  "validTimeUtc": [
    1658660400,
    1658746800,
    1658833200,
    1658919600,
    1659006000,
    1659092400,
    1659178800,
    1659265200
  ],
  "daypart": [
    {
      "cloudCover": [
        31,
        51,
        78,
        74,
        69,
        46,
        67,
        76,
        74,
        63,
        65,
        51,
        51,
        56,
        69,
        62
      ],
      "dayOrNight": [
        "D",
        "N",
        "D",
        "N",
        "D",
        "N",
        "D",
        "N",
        "D",
        "N",
        "D",
        "N",
        "D",
        "N",
        "D",
        "N"
      ],
      "daypartName": [
        "Today",
        "Tonight",
        "Tomorrow",
        "Tomorrow night",
        "Tuesday",
        "Tuesday night",
        "Wednesday",
        "Wednesday night",
        "Thursday",
        "Thursday night",
        "Friday",
        "Friday night",
        "Saturday",
        "Saturday night",
        "Sunday",
        "Sunday night"
      ],
      "iconCode": [
        30,
        29,
        38,
        47,
        30,
        29,
        30,
        47,
        38,
        47,
        39,
        45,
        30,
        29,
        28,
        45
      ],
      "iconCodeExtend": [
        3000,
        2900,
        7203,
        6200,
        9003,
        2900,
        3000,
        3809,
        6203,
        3709,
        6103,
        6100,
        3000,
        2900,
        2800,
        7100
      ],
      "narrative": [
        "Partly cloudy. Near record high temperatures. High 97F. Winds SW at 10 to 15 mph.",
        "Partly cloudy skies. Low around 80F. Winds SSW at 5 to 10 mph.",
        "Cloudy skies during the morning hours followed by thunderstorms in the afternoon. Potential for severe thunderstorms. High 91F. Winds SW at 5 to 10 mph. Chance of rain 80%.",
        "Scattered thunderstorms in the evening, with mostly cloudy skies overnight. Low near 70F. Winds WSW at 5 to 10 mph. Chance of rain 50%.",
        "Cloudy early with partial sunshine expected late. High near 85F. Winds WNW at 5 to 10 mph.",
        "Partly cloudy. Low 68F. Winds light and variable.",
        "Partly cloudy skies in the morning will give way to cloudy skies during the afternoon. A stray shower or thunderstorm is possible. High 86F. Winds SW at 5 to 10 mph.",
        "Variable clouds with thunderstorms, especially during the evening. Low 73F. Winds SW at 5 to 10 mph. Chance of rain 40%.",
        "Scattered thunderstorms in the morning, then mainly cloudy late. High 91F. Winds WSW at 5 to 10 mph. Chance of rain 40%.",
        "Partly to mostly cloudy with widely scattered showers or thunderstorms possible later at night. Low 71F. Winds W at 5 to 10 mph. Chance of rain 40%.",
        "Showers in the morning with some clearing in the afternoon. High 89F. Winds W at 5 to 10 mph. Chance of rain 40%.",
        "A shower or two possible early with partly cloudy skies later at night. Low 67F. Winds WNW at 5 to 10 mph. Chance of rain 30%.",
        "Intervals of clouds and sunshine. High 88F. Winds light and variable.",
        "Partly cloudy early with increasing clouds overnight. Low 68F. Winds light and variable.",
        "Mainly cloudy. High 87F. Winds light and variable.",
        "Increasing clouds with showers arriving sometime after midnight. Low 69F. Winds light and variable. Chance of rain 40%."
      ],
      "precipChance": [
        2,
        8,
        77,
        47,
        9,
        24,
        24,
        40,
        35,
        39,
        39,
        34,
        10,
        23,
        24,
        35
      ],
      "precipType": [
        "rain",
        "rain",
        "rain",
        "rain",
        "rain",
        "rain",
        "rain",
        "rain",
        "rain",
        "rain",
        "rain",
        "rain",
        "rain",
        "rain",
        "rain",
        "rain"
      ],
      "qpf": [
        0,
        0,
        0.34,
        0.1,
        0,
        0,
        0,
        0.06,
        0.03,
        0.09,
        0.02,
        0.07,
        0,
        0,
        0,
        0.02
      ],
      "qpfSnow": [
        0,
        0,
        0,
        0,
        0,
        0,
        0,
        0,
        0,
        0,
        0,
        0,
        0,
        0,
        0,
        0
      ],
      "qualifierCode": [
        "Q615",
        null,
        "Q9605",
        null,
        null,
        null,
        "Q8001",
        null,
        null,
        null,
        null,
        null,
        null,
        null,
        null,
        null
      ],
      "qualifierPhrase": [
        "Near record high temperatures.",
        null,
        "Potential for severe thunderstorms.",
        null,
        null,
        null,
        "A stray shower or thunderstorm is possible.",
        null,
        null,
        null,
        null,
        null,
        null,
        null,
        null,
        null
      ],
      "relativeHumidity": [
        35,
        61,
        64,
        86,
        58,
        80,
        64,
        82,
        64,
        73,
        60,
        69,
        50,
        69,
        59,
        79
      ],
      "snowRange": [
        "",
        "",
        "",
        "",
        "",
        "",
        "",
        "",
        "",
        "",
        "",
        "",
        "",
        "",
        "",
        ""
      ],
      "temperature": [
        97,
        80,
        91,
        70,
        85,
        68,
        86,
        73,
        91,
        71,
        89,
        67,
        88,
        68,
        87,
        69
      ],
      "temperatureHeatIndex": [
        100,
        97,
        98,
        85,
        86,
        82,
        88,
        87,
        95,
        91,
        91,
        87,
        88,
        84,
        89,
        85
      ],
      "temperatureWindChill": [
        94,
        80,
        80,
        70,
        72,
        68,
        71,
        73,
        75,
        71,
        74,
        67,
        70,
        68,
        71,
        69
      ],
      "thunderCategory": [
        "No thunder",
        "No thunder",
        "Severe thunderstorms possible",
        "Thunder expected",
        "No thunder",
        "No thunder",
        "Thunder possible",
        "Thunder expected",
        "Thunder expected",
        "Thunder expected",
        "No thunder",
        "No thunder",
        "No thunder",
        "No thunder",
        "No thunder",
        "No thunder"
      ],
      "thunderIndex": [
        0,
        0,
        3,
        2,
        0,
        0,
        1,
        2,
        2,
        2,
        0,
        0,
        0,
        0,
        0,
        0
      ],
      "uvDescription": [
        "Very High",
        "Low",
        "High",
        "Low",
        "High",
        "Low",
        "High",
        "Low",
        "High",
        "Low",
        "High",
        "Low",
        "Very High",
        "Low",
        "High",
        "Low"
      ],
      "uvIndex": [
        9,
        0,
        7,
        0,
        7,
        0,
        7,
        0,
        6,
        0,
        7,
        0,
        8,
        0,
        7,
        0
      ],
      "windDirection": [
        224,
        205,
        229,
        258,
        292,
        238,
        234,
        224,
        258,
        265,
        269,
        297,
        308,
        283,
        208,
        214
      ],
      "windDirectionCardinal": [
        "SW",
        "SSW",
        "SW",
        "WSW",
        "WNW",
        "WSW",
        "SW",
        "SW",
        "WSW",
        "W",
        "W",
        "WNW",
        "NW",
        "WNW",
        "SSW",
        "SW"
      ],
      "windPhrase": [
        "Winds SW at 10 to 15 mph.",
        "Winds SSW at 5 to 10 mph.",
        "Winds SW at 5 to 10 mph.",
        "Winds WSW at 5 to 10 mph.",
        "Winds WNW at 5 to 10 mph.",
        "Winds light and variable.",
        "Winds SW at 5 to 10 mph.",
        "Winds SW at 5 to 10 mph.",
        "Winds WSW at 5 to 10 mph.",
        "Winds W at 5 to 10 mph.",
        "Winds W at 5 to 10 mph.",
        "Winds WNW at 5 to 10 mph.",
        "Winds light and variable.",
        "Winds light and variable.",
        "Winds light and variable.",
        "Winds light and variable."
      ],
      "windSpeed": [
        11,
        10,
        10,
        7,
        6,
        6,
        7,
        6,
        9,
        7,
        8,
        7,
        6,
        5,
        6,
        5
      ],
      "wxPhraseLong": [
        "Partly Cloudy",
        "Partly Cloudy",
        "PM Thunderstorms",
        "Thunderstorms Early",
        "AM Clouds/PM Sun",
        "Partly Cloudy",
        "Partly Cloudy",
        "Scattered Thunderstorms",
        "AM Thunderstorms",
        "Isolated Thunderstorms",
        "AM Showers",
        "Showers Early",
        "Partly Cloudy",
        "Partly Cloudy",
        "Mostly Cloudy",
        "Showers Late"
      ],
      "wxPhraseShort": [
        "P Cloudy",
        "P Cloudy",
        "PM T-Storms",
        "T-Storms",
        "AM Clouds",
        "P Cloudy",
        "P Cloudy",
        "Sct T-Storms",
        "AM T-Storms",
        "Iso T-Storms",
        "AM Showers",
        "Shwrs Early",
        "P Cloudy",
        "P Cloudy",
        "M Cloudy",
        "Shwrs Late"
      ]
    }
  ]
}
