{
  "observations": [
    {
      "stationID": "KPACREST5",
      "obsTimeUtc": "2022-02-20T17:57:15Z",
      "obsTimeLocal": "2022-02-20 12:57:15",
      "neighborhood": "Cannon Run West",
      "softwareType": "AMBWeatherV3.0.3",
      "country": "US",
      "solarRadiation": 508.4,
      "lon": -75.390785,
      "realtimeFrequency": null,
      "epoch": 1645379835,
      "lat": 40.109383,
      "uv": 5,
      "winddir": 148,
      "humidity": 34,
      "qcStatus": 1,
      "imperial": {
        "temp": 38,
        "heatIndex": 38,
        "dewpt": 12,
        "windChill": 38,
        "windSpeed": 2,
        "windGust": 2,
        "pressure": 30.25,
        "precipRate": 0,
        "precipTotal": 0,
        "elev": 170
      }
    }
  ]
}
